{
  "Title":      "Jena Core",
  "SourceUrl":  "http://central.maven.org/maven2/org/apache/jena/jena-core/",
  "Tracker":    "https://abi-laboratory.pro/java/tracker/timeline/jena-core/",
  "Maintainer": "Andrey P.",

  "Reports": [
  {
    "Version":           "3.4.0",
    "From":              "3.3.0",
    "BC":                "100%",
    "Added":             2,
    "Removed":           0,
    "TotalProblems":     0,
    "Src_BC":            "100%",
    "Src_TotalProblems": 0,
    "ArchivesAdded":     0,
    "ArchivesRemoved":   0,
    "TotalArchives":     1
  },
  {
    "Version":           "3.3.0",
    "From":              "3.2.0",
    "BC":                "100%",
    "Added":             80,
    "Removed":           0,
    "TotalProblems":     0,
    "Src_BC":            "100%",
    "Src_TotalProblems": 0,
    "ArchivesAdded":     0,
    "ArchivesRemoved":   0,
    "TotalArchives":     1
  },
  {
    "Version":           "3.2.0",
    "From":              "3.1.1",
    "BC":                "98.3%",
    "Added":             7,
    "Removed":           0,
    "TotalProblems":     2,
    "Src_BC":            "90.9%",
    "Src_TotalProblems": 3,
    "ArchivesAdded":     0,
    "ArchivesRemoved":   0,
    "TotalArchives":     1
  },
  {
    "Version":           "3.1.1",
    "From":              "3.1.0",
    "BC":                "99.5%",
    "Added":             51,
    "Removed":           14,
    "TotalProblems":     13,
    "Src_BC":            "76.8%",
    "Src_TotalProblems": 24,
    "ArchivesAdded":     0,
    "ArchivesRemoved":   0,
    "TotalArchives":     1
  },
  {
    "Version":           "3.1.0",
    "From":              "3.0.1",
    "BC":                "93.1%",
    "Added":             12,
    "Removed":           293,
    "TotalProblems":     28,
    "Src_BC":            "90.1%",
    "Src_TotalProblems": 29,
    "ArchivesAdded":     0,
    "ArchivesRemoved":   0,
    "TotalArchives":     1
  },
  {
    "Version":           "3.0.1",
    "From":              "3.0.0",
    "BC":                "99.9%",
    "Added":             52,
    "Removed":           1,
    "TotalProblems":     5,
    "Src_BC":            "99.9%",
    "Src_TotalProblems": 5,
    "ArchivesAdded":     0,
    "ArchivesRemoved":   0,
    "TotalArchives":     1
  }]
}
